{
	"info": {
		"_postman_id": "735f1fd3-2d07-4016-9d59-d712dd860eea",
		"name": "Resplash laravel",
		"schema": "https://schema.getpostman.com/json/collection/v2.0.0/collection.json",
		"_exporter_id": "21938634"
	},
	"item": [
		{
			"name": "home latest",
			"request": {
				"method": "GET",
				"header": [
					{
						"key": "Accept",
						"value": "application/json",
						"type": "text"
					}
				],
				"url": {
					"raw": "https://unsplashandweather.brijeshnavadiya.com/api/unsplash/photos?client_id=ece4fa5efbe76bcec26bf982d7b7ef8b27bd80d832dbe8a40bd954448fc4320a&page=1&per_page=30&order_by=latest",
					"protocol": "https",
					"host": [
						"unsplashandweather",
						"brijeshnavadiya",
						"com"
					],
					"path": [
						"api",
						"unsplash",
						"photos"
					],
					"query": [
						{
							"key": "client_id",
							"value": "ece4fa5efbe76bcec26bf982d7b7ef8b27bd80d832dbe8a40bd954448fc4320a"
						},
						{
							"key": "page",
							"value": "1"
						},
						{
							"key": "per_page",
							"value": "30"
						},
						{
							"key": "order_by",
							"value": "latest"
						}
					]
				}
			},
			"response": []
		},
		{
			"name": "collection all",
			"request": {
				"method": "GET",
				"header": [
					{
						"key": "Accept",
						"value": "application/json",
						"type": "text"
					}
				],
				"url": {
					"raw": "https://unsplashandweather.brijeshnavadiya.com/api/unsplash/collections?client_id=ece4fa5efbe76bcec26bf982d7b7ef8b27bd80d832dbe8a40bd954448fc4320a&page=1&per_page=30",
					"protocol": "https",
					"host": [
						"unsplashandweather",
						"brijeshnavadiya",
						"com"
					],
					"path": [
						"api",
						"unsplash",
						"collections"
					],
					"query": [
						{
							"key": "client_id",
							"value": "ece4fa5efbe76bcec26bf982d7b7ef8b27bd80d832dbe8a40bd954448fc4320a"
						},
						{
							"key": "page",
							"value": "1"
						},
						{
							"key": "per_page",
							"value": "30"
						}
					]
				}
			},
			"response": []
		},
		{
			"name": "sub collection",
			"request": {
				"method": "GET",
				"header": [
					{
						"key": "Accept",
						"value": "application/json",
						"type": "text"
					}
				],
				"url": {
					"raw": "https://unsplashandweather.brijeshnavadiya.com/api/unsplash/collections/photos?client_id=ece4fa5efbe76bcec26bf982d7b7ef8b27bd80d832dbe8a40bd954448fc4320a&page=1&per_page=30",
					"protocol": "https",
					"host": [
						"unsplashandweather",
						"brijeshnavadiya",
						"com"
					],
					"path": [
						"api",
						"unsplash",
						"collections",
						"photos"
					],
					"query": [
						{
							"key": "client_id",
							"value": "ece4fa5efbe76bcec26bf982d7b7ef8b27bd80d832dbe8a40bd954448fc4320a"
						},
						{
							"key": "page",
							"value": "1"
						},
						{
							"key": "per_page",
							"value": "30"
						}
					]
				}
			},
			"response": []
		}
	]
}